cfg/__init__.py
cfg/cfg.py
cfg/utils.py
cfg_manager-1.1.6.dist-info/DESCRIPTION.rst
cfg_manager-1.1.6.dist-info/METADATA
cfg_manager-1.1.6.dist-info/RECORD
cfg_manager-1.1.6.dist-info/WHEEL
cfg_manager-1.1.6.dist-info/entry_points.txt
cfg_manager-1.1.6.dist-info/metadata.json
cfg_manager-1.1.6.dist-info/top_level.txt
