Metadata-Version: 2.0
Name: cfg-manager
Version: 1.1.6
Summary: git based config files manager and installer
Home-page: https://github.com/freddez/cfg
Author: Frédéric de ZORZI
Author-email: f@idez.net
License: UNKNOWN
Project-URL: Bug Reports, https://github.com/freddez/cfg/issues
Project-URL: Funding, https://donate.pypi.org
Project-URL: Say Thanks!, https://saythanks.io/to/freddez
Project-URL: Source, https://github.com/freddez/cfg
Keywords: system configuration files git deploy
Platform: UNKNOWN
Classifier: Development Status :: 4 - Beta
Classifier: Intended Audience :: System Administrators
Classifier: Topic :: Software Development :: Build Tools
Classifier: License :: OSI Approved :: GNU General Public License v3 or later (GPLv3+)
Classifier: Programming Language :: Python :: 3
Classifier: Programming Language :: Python :: 3.5
Classifier: Programming Language :: Python :: 3.6
Classifier: Programming Language :: Python :: 3.7
Requires-Python: >=3.5.*, <4
Requires-Dist: gitpython
Requires-Dist: colorama
Requires-Dist: termcolor
